{
  "page_count": 1,
  "page_size": 30,
  "total_records": 9,
  "next_page_token": "",
  "participants": [
    {
      "id": "tK0fhuMFSCK5mhbwubrHTg",
      "user_id": "16778240",
      "name": "RubiKamp instructor",
      "user_email": "rubikampiran@gmail.com",
      "join_time": "2024-02-19T14:30:03Z",
      "leave_time": "2024-02-19T15:30:59Z",
      "duration": 3656,
      "attentiveness_score": "",
      "failover": false,
      "status": "in_meeting",
      "customer_key": "",
      "participant_user_id": "tK0fhuMFSCK5mhbwubrHTg"
    },
    {
      "id": "",
      "user_id": "16795648",
      "name": "fateme",
      "user_email": "",
      "join_time": "2024-02-19T14:30:11Z",
      "leave_time": "2024-02-19T15:30:56Z",
      "duration": 3645,
      "attentiveness_score": "",
      "failover": false,
      "status": "in_meeting",
      "customer_key": ""
    },
    {
      "id": "",
      "user_id": "16796672",
      "name": "Amir Mohammad",
      "user_email": "",
      "join_time": "2024-02-19T14:30:16Z",
      "leave_time": "2024-02-19T15:31:01Z",
      "duration": 3645,
      "attentiveness_score": "",
      "failover": false,
      "status": "in_meeting",
      "customer_key": ""
    },
    {
      "id": "",
      "user_id": "16797696",
      "name": "Bahareh Mohammadzadeh",
      "user_email": "",
      "join_time": "2024-02-19T14:30:33Z",
      "leave_time": "2024-02-19T14:32:05Z",
      "duration": 92,
      "attentiveness_score": "",
      "failover": false,
      "status": "in_meeting",
      "customer_key": ""
    },
    {
      "id": "",
      "user_id": "16798720",
      "name": "Sajjad Fazel Yazdi",
      "user_email": "",
      "join_time": "2024-02-19T14:30:36Z",
      "leave_time": "2024-02-19T15:30:59Z",
      "duration": 3623,
      "attentiveness_score": "",
      "failover": false,
      "status": "in_meeting",
      "customer_key": ""
    },
    {
      "id": "",
      "user_id": "16799744",
      "name": "Ramin 2007",
      "user_email": "",
      "join_time": "2024-02-19T14:31:45Z",
      "leave_time": "2024-02-19T15:30:57Z",
      "duration": 3552,
      "attentiveness_score": "",
      "failover": false,
      "status": "in_meeting",
      "customer_key": ""
    },
    {
      "id": "",
      "user_id": "16800768",
      "name": "Bahareh Mohammadzadeh",
      "user_email": "",
      "join_time": "2024-02-19T14:32:05Z",
      "leave_time": "2024-02-19T15:30:59Z",
      "duration": 3534,
      "attentiveness_score": "",
      "failover": false,
      "status": "in_meeting",
      "customer_key": ""
    },
    {
      "id": "",
      "user_id": "16801792",
      "name": "Narges Aghabeygi",
      "user_email": "",
      "join_time": "2024-02-19T14:32:19Z",
      "leave_time": "2024-02-19T15:23:07Z",
      "duration": 3048,
      "attentiveness_score": "",
      "failover": false,
      "status": "in_meeting",
      "customer_key": ""
    },
    {
      "id": "",
      "user_id": "16802816",
      "name": "Narges Aghabeygi",
      "user_email": "",
      "join_time": "2024-02-19T15:24:51Z",
      "leave_time": "2024-02-19T15:30:56Z",
      "duration": 365,
      "attentiveness_score": "",
      "failover": false,
      "status": "in_meeting",
      "customer_key": ""
    }
  ]
}